{
  "af": "south-asia",
  "al": "europe",
  "dz": "africa",
  "ao": "africa",
  "ar": "south-america",
  "am": "central-asia",
  "au": "australia-oceania",
  "at": "europe",
  "az": "central-asia",
  "bd": "south-asia",
  "by": "europe",
  "be": "europe",
  "bz": "central-america-n-caribbean",
  "bj": "africa",
  "bo": "south-america",
  "ba": "europe",
  "bw": "africa",
  "br": "south-america",
  "bn": "east-n-southeast-asia",
  "bg": "europe",
  "bf": "africa",
  "bi": "africa",
  "kh": "east-n-southeast-asia",
  "cm": "africa",
  "ca": "north-america",
  "cv": "africa",
  "cf": "africa",
  "td": "africa",
  "cl": "south-america",
  "cn": "east-n-southeast-asia",
  "co": "south-america",
  "km": "africa",
  "cg": "africa",
  "cd": "africa",
  "cr": "central-america-n-caribbean",
  "hr": "europe",
  "cu": "central-america-n-caribbean",
  "cy": "middle-east",
  "cz": "europe",
  "dk": "europe",
  "dj": "africa",
  "dm": "central-america-n-caribbean",
  "do": "central-america-n-caribbean",
  "ec": "south-america",
  "eg": "africa",
  "sv": "central-america-n-caribbean",
  "gq": "africa",
  "er": "africa",
  "ee": "europe",
  "sz": "africa",
  "et": "africa",
  "fj": "australia-oceania",
  "fi": "europe",
  "fr": "europe",
  "ga": "africa",
  "gm": "africa",
  "ge": "central-asia",
  "de": "europe",
  "gh": "africa",
  "gr": "europe",
  "gd": "central-america-n-caribbean",
  "gt": "central-america-n-caribbean",
  "gn": "africa",
  "ag": "africa",
  "gw": "africa",
  "gy": "south-america",
  "ht": "central-america-n-caribbean",
  "hn": "central-america-n-caribbean",
  "hu": "europe",
  "is": "europe",
  "in": "south-asia",
  "id": "east-n-southeast-asia",
  "ir": "middle-east",
  "iq": "middle-east",
  "ie": "europe",
  "il": "middle-east",
  "it": "europe",
  "ci": "africa",
  "jm": "central-america-n-caribbean",
  "jp": "east-n-southeast-asia",
  "jo": "middle-east",
  "kz": "central-asia",
  "ke": "africa",
  "ki": "australia-oceania",
  "kp": "east-n-southeast-asia",
  "kr": "east-n-southeast-asia",
  "kw": "middle-east",
  "kg": "central-asia",
  "la": "east-n-southeast-asia",
  "lv": "europe",
  "lb": "middle-east",
  "ls": "africa",
  "lr": "africa",
  "ly": "africa",
  "lt": "europe",
  "lu": "europe",
  "mg": "africa",
  "mw": "africa",
  "my": "east-n-southeast-asia",
  "mv": "south-asia",
  "ml": "africa",
  "mt": "europe",
  "mh": "australia-oceania",
  "mr": "africa",
  "mu": "africa",
  "mx": "north-america",
  "fm": "australia-oceania",
  "md": "europe",
  "mc": "europe",
  "mn": "central-asia",
  "me": "europe",
  "ma": "africa",
  "mz": "africa",
  "mm": "east-n-southeast-asia",
  "na": "africa",
  "nr": "australia-oceania",
  "np": "south-asia",
  "nl": "europe",
  "nz": "australia-oceania",
  "ni": "central-america-n-caribbean",
  "ne": "africa",
  "ng": "africa",
  "mk": "europe",
  "no": "europe",
  "om": "middle-east",
  "pk": "south-asia",
  "pw": "australia-oceania",
  "pa": "central-america-n-caribbean",
  "pg": "australia-oceania",
  "py": "south-america",
  "pe": "south-america",
  "ph": "east-n-southeast-asia",
  "pl": "europe",
  "po": "europe",
  "qa": "middle-east",
  "ro": "europe",
  "ru": "europe",
  "rw": "africa",
  "kn": "central-america-n-caribbean",
  "lc": "central-america-n-caribbean",
  "vc": "central-america-n-caribbean",
  "ws": "australia-oceania",
  "sm": "europe",
  "st": "africa",
  "sa": "middle-east",
  "sn": "africa",
  "rs": "europe",
  "sc": "africa",
  "sl": "africa",
  "sg": "east-n-southeast-asia",
  "sk": "europe",
  "si": "europe",
  "sb": "australia-oceania",
  "so": "africa",
  "za": "africa",
  "ss": "africa",
  "es": "europe",
  "lk": "south-asia",
  "sd": "africa",
  "sr": "south-america",
  "se": "europe",
  "ch": "europe",
  "sy": "middle-east",
  "tw": "east-n-southeast-asia",
  "tj": "central-asia",
  "tz": "africa",
  "th": "east-n-southeast-asia",
  "tl": "east-n-southeast-asia",
  "tg": "africa",
  "to": "australia-oceania",
  "tt": "central-america-n-caribbean",
  "tn": "africa",
  "tr": "middle-east",
  "tm": "central-asia",
  "tv": "australia-oceania",
  "ug": "africa",
  "ua": "europe",
  "ae": "middle-east",
  "gb": "europe",
  "us": "north-america",
  "uy": "south-america",
  "uz": "central-asia",
  "vu": "australia-oceania",
  "ve": "south-america",
  "vn": "east-n-southeast-asia",
  "ye": "middle-east",
  "zm": "africa",
  "zw": "africa"
}
